{
  "$schema": "https://json-schema.org/draft/2020-12/schema",
  "version": 2,
  "$comment": "Single source of truth for the Storybook IA. .storybook/preview.jsx imports storySortOrder from this file \u2014 edit here, never there. Grammar: docs/plans/2026-07-12-001-feat-ds-docs-ia-upgrade-plan.md",
  "titlePrefixes": [
    "Getting started/",
    "Foundations/",
    "Components/",
    "Data visualizations/",
    "Specs/",
    "Deprecated/"
  ],
  "componentGroups": {
    "Actions": [
      "Button",
      "Button group"
    ],
    "Forms and inputs": [
      "Cascader",
      "Checkbox",
      "Choice grid",
      "Date picker",
      "Date & time picker",
      "Dropdown",
      "File upload",
      "Input",
      "Input group",
      "Label & caption",
      "Multiple choice",
      "Number input",
      "Radio",
      "Range",
      "Rating",
      "Rich text editor",
      "Scale",
      "Select",
      "Switch",
      "Textarea",
      "Tree select"
    ],
    "Layout and structure": [
      "Accordion",
      "Card",
      "Carousel",
      "Collapse",
      "Divider",
      "Jumbotron",
      "List group",
      "Media object",
      "Scroll bar"
    ],
    "Messaging": [
      "Alert",
      "Modal",
      "Toast"
    ],
    "Navigation": [
      "Breadcrumb",
      "Nav pills",
      "Nav tabs",
      "Pagination",
      "Scrollspy",
      "Sidebar tab"
    ],
    "Overlays": [
      "Popover",
      "Tooltip"
    ],
    "Status and loading": [
      "Badge",
      "Loading",
      "Progress"
    ]
  },
  "specTypeOrder": [
    "Overview",
    "Elements",
    "Cards",
    "Tables",
    "Modals",
    "Sections",
    "Pages"
  ],
  "flatTitleGroups": [],
  "docsFirstGroups": [
    "Components"
  ],
  "docsFirstTag": "!dev",
  "storySortOrder": [
    "Getting started",
    [
      "Introduction"
    ],
    "Foundations",
    [
      "Introduction",
      "Color",
      "Typography",
      "Layout & grid",
      "Grid",
      "Spacing",
      "Patterns",
      [
        "Introduction",
        "Surfaces",
        "Surface container",
        "Card",
        "Section",
        "Modal",
        "Table"
      ],
      "Elevation",
      "Iconography",
      "Logos",
      "Imagery",
      "Design tokens",
      "Accessibility"
    ],
    "Components",
    [
      "Actions",
      [
        "Button",
        "Button group"
      ],
      "Forms and inputs",
      [
        "Cascader",
        "Checkbox",
        "Choice grid",
        "Date picker",
        "Date & time picker",
        "Dropdown",
        "File upload",
        "Input",
        "Input group",
        "Label & caption",
        "Multiple choice",
        "Number input",
        "Radio",
        "Range",
        "Rating",
        "Rich text editor",
        "Scale",
        "Select",
        "Switch",
        "Textarea",
        "Tree select"
      ],
      "Layout and structure",
      [
        "Accordion",
        "Card",
        "Carousel",
        "Collapse",
        "Divider",
        "Jumbotron",
        "List group",
        "Media object",
        "Scroll bar"
      ],
      "Messaging",
      [
        "Alert",
        "Modal",
        "Toast"
      ],
      "Navigation",
      [
        "Breadcrumb",
        "Nav pills",
        "Nav tabs",
        "Pagination",
        "Scrollspy",
        "Sidebar tab"
      ],
      "Overlays",
      [
        "Popover",
        "Tooltip"
      ],
      "Status and loading",
      [
        "Badge",
        "Loading",
        "Progress"
      ]
    ],
    "Data visualizations",
    [
      "Comparison",
      "Correlation",
      "Distribution",
      "Flow & relationships",
      "Part-to-whole",
      "Temporal"
    ],
    "Specs",
    [
      "Universal",
      [
        "Overview",
        "Elements",
        [
          "Smart Badges"
        ],
        "Cards",
        "Tables",
        "Modals",
        "Sections",
        "Pages"
      ],
      "Login",
      [
        "Overview",
        "Elements",
        "Cards",
        "Tables",
        "Modals",
        "Sections",
        "Pages"
      ],
      "Home",
      [
        "Overview",
        "Elements",
        "Cards",
        "Tables",
        "Modals",
        "Sections",
        "Pages"
      ],
      "Profile",
      [
        "Overview",
        "Elements",
        "Cards",
        "Tables",
        "Modals",
        "Sections",
        "Pages"
      ],
      "Training",
      [
        "Overview",
        "Onboarding",
        [
          "Overview",
          "Elements",
          "Cards",
          "Tables",
          "Modals",
          "Sections",
          "Pages"
        ],
        "Lessons",
        [
          "Overview",
          "Elements",
          "Cards",
          "Tables",
          "Modals",
          "Sections",
          "Pages"
        ]
      ],
      "Toolkit",
      [
        "Overview",
        "Pre-Session",
        [
          "Overview",
          "Elements",
          "Cards",
          "Tables",
          "Modals",
          "Sections",
          "Pages"
        ],
        "In-Session",
        [
          "Overview",
          "Elements",
          "Cards",
          "Tables",
          "Modals",
          "Sections",
          "Pages"
        ],
        "Post-Session",
        [
          "Overview",
          "Elements",
          "Cards",
          "Tables",
          "Modals",
          "Sections",
          "Pages"
        ]
      ],
      "Admin",
      [
        "Overview",
        "Tutor",
        [
          "Overview",
          "Elements",
          "Cards",
          "Tables",
          "Modals",
          "Sections",
          "Pages"
        ],
        "Session",
        [
          "Overview",
          "Elements",
          "Cards",
          "Tables",
          "Modals",
          "Sections",
          "Pages"
        ],
        "Student",
        [
          "Overview",
          "Elements",
          "Cards",
          "Tables",
          "Modals",
          "Sections",
          "Pages"
        ],
        "Group",
        [
          "Overview",
          "Elements",
          "Cards",
          "Tables",
          "Modals",
          "Sections",
          "Pages"
        ]
      ]
    ],
    "Deprecated",
    "*"
  ],
  "docsSpine": [
    "Content",
    "Styles",
    "Sizes",
    "Interaction States",
    "Layout",
    "Interactive"
  ],
  "docsSpineExceptions": [
    "Anatomy",
    "Behavior",
    "Types"
  ],
  "lifecycle": {
    "tags": [
      "wip",
      "beta",
      "deprecated"
    ],
    "$comment": "[wip] -> [beta] -> stable (untagged) -> [deprecated]; same tags used as Figma frame/page prefixes."
  }
}